{
  "id": "MachineNonTCPInterpolationMode",
  "title": "MachineNonTCPInterpolationMode Enumerator",
  "type": "class",
  "namespace": "adsk::cam",
  "header_file": "Cam\\CamTypeDefs.h",
  "description": "Interpolation modes available for non-TCP motions. Defined in namespace \"adsk::cam\" and the header file is <Cam\\CamTypeDefs.h>",
  "parent_class": "",
  "methods": [
    {
      "name": "MachineNonTCPInterpolationMode_IndependentAxes",
      "description": "1"
    },
    {
      "name": "MachineNonTCPInterpolationMode_SynchronizedAxes",
      "description": "0"
    }
  ],
  "version": "Introduced in version September 2025"
}